mysqltuner_mcp/__init__.py
mysqltuner_mcp/__main__.py
mysqltuner_mcp/server.py
mysqltuner_mcp/services/__init__.py
mysqltuner_mcp/services/db_pool.py
mysqltuner_mcp/services/sql_driver.py
mysqltuner_mcp/tools/__init__.py
mysqltuner_mcp/tools/toolhandler.py
mysqltuner_mcp/tools/tools_engines.py
mysqltuner_mcp/tools/tools_health.py
mysqltuner_mcp/tools/tools_index.py
mysqltuner_mcp/tools/tools_innodb.py
mysqltuner_mcp/tools/tools_memory.py
mysqltuner_mcp/tools/tools_performance.py
mysqltuner_mcp/tools/tools_replication.py
mysqltuner_mcp/tools/tools_security.py
mysqltuner_mcp/tools/tools_statements.py
mysqltuner_mcp-0.1.2.dist-info/METADATA
mysqltuner_mcp-0.1.2.dist-info/WHEEL
mysqltuner_mcp-0.1.2.dist-info/entry_points.txt
mysqltuner_mcp-0.1.2.dist-info/licenses/LICENSE
mysqltuner_mcp-0.1.2.dist-info/RECORD
