Metadata-Version: 2.4
Name: mysqltuner_mcp
Version: 0.1.2
Summary: MySQL MCP Performance Tuning Server - AI-powered MySQL performance tuning capabilities
Project-URL: Homepage, https://github.com/isdaniel/mysqltuner_mcp
Project-URL: Repository, https://github.com/isdaniel/mysqltuner_mcp
Project-URL: Issues, https://github.com/isdaniel/mysqltuner_mcp/issues
Author-email: DanielShih <dog830228@gmail.com>
License: Apache-2.0
License-File: LICENSE
Keywords: ai,database,mcp,mysql,performance,tuning
Requires-Python: >=3.10
Requires-Dist: aiomysql>=0.2.0
Requires-Dist: mcp[cli]>=1.12.0
Requires-Dist: pymysql>=1.1.0
Provides-Extra: dev
Requires-Dist: black>=25.11.0; extra == 'dev'
Requires-Dist: pytest-asyncio>=1.3.0; extra == 'dev'
Requires-Dist: pytest-cov>=7.0.0; extra == 'dev'
Requires-Dist: pytest>=9.0.1; extra == 'dev'
Requires-Dist: ruff>=0.14.6; extra == 'dev'
Provides-Extra: http
Requires-Dist: starlette>=0.27.0; extra == 'http'
Requires-Dist: uvicorn>=0.23.0; extra == 'http'
